calculationengine/__init__.py
calculationengine/calculate.py
calculationengine-0.1.1.dist-info/licenses/LICENSE
calculationengine-0.1.1.dist-info/METADATA
calculationengine-0.1.1.dist-info/WHEEL
calculationengine-0.1.1.dist-info/top_level.txt
calculationengine-0.1.1.dist-info/RECORD
