Metadata-Version: 2.4
Name: calculationengine
Version: 0.1.1
Summary: A simple Python calculator library
Author-email: Gowri Sankar <thegowrisankar@gmail.com>
License: MIT
Project-URL: Homepage, https://github.com/GowriSankar-GSG/calculationengine/
Project-URL: Repository, https://github.com/GowriSankar-GSG/calculationengine/
Keywords: calculator,math,python,library,simple,ease,useful,basic
Requires-Python: >=3.8
License-File: LICENSE
Dynamic: license-file
